fbc/__init__.py
fbc/__main__.py
Flask_Boilerplate_Creator-0.0.4.dist-info/LICENSE
Flask_Boilerplate_Creator-0.0.4.dist-info/METADATA
Flask_Boilerplate_Creator-0.0.4.dist-info/WHEEL
Flask_Boilerplate_Creator-0.0.4.dist-info/top_level.txt
Flask_Boilerplate_Creator-0.0.4.dist-info/RECORD
