Metadata-Version: 2.1
Name: Flask Boilerplate Creator
Version: 0.0.4
Summary: Create boilerplate structure of flask web application
Home-page: https://github.com/hakiKhuva/flask-boilerplate-creator
Author: Harkishan Khuva
Author-email: hakitechy@gmail.com
License: MIT
Keywords: fbc,flask-boilerplate-creator,flask boilerplate creator
Platform: UNKNOWN
Classifier: Environment :: Console
Classifier: Intended Audience :: Developers
Classifier: Programming Language :: Python :: 3
Classifier: License :: OSI Approved :: MIT License
Classifier: Operating System :: OS Independent
Requires-Python: >=3.8
License-File: LICENSE
